thorvg_python/__init__.py
thorvg_python/base.py
thorvg_python/engine.py
thorvg_python/libthorvg.dylib
thorvg_python/py.typed
thorvg_python/saver.py
thorvg_python/animation/__init__.py
thorvg_python/animation/lottie.py
thorvg_python/canvas/__init__.py
thorvg_python/canvas/sw.py
thorvg_python/gradient/__init__.py
thorvg_python/gradient/linear.py
thorvg_python/gradient/radial.py
thorvg_python/paint/__init__.py
thorvg_python/paint/picture.py
thorvg_python/paint/scene.py
thorvg_python/paint/shape.py
thorvg_python/paint/text.py
thorvg_python-1.0.1.dist-info/licenses/LICENSE
thorvg_python-1.0.1.dist-info/METADATA
thorvg_python-1.0.1.dist-info/WHEEL
thorvg_python-1.0.1.dist-info/top_level.txt
thorvg_python-1.0.1.dist-info/RECORD
