Metadata-Version: 2.4
Name: thorvg-python
Version: 1.0.1
Summary: A ctypes API for thorvg, a vector graphics engine supporting SVG and Lottie formats.
Author-email: chaudominic <chaudominic2@gmail.com>
License:                   GNU LESSER GENERAL PUBLIC LICENSE
Project-URL: Repository, https://github.com/laggykiller/thorvg-python
Project-URL: Documentation, https://thorvg-python.readthedocs.io/en/latest/
Project-URL: Tracker, https://github.com/laggykiller/thorvg-python/issues
Keywords: thorvg,lottie,svg,ctypes,python
Classifier: Topic :: Multimedia :: Graphics
Requires-Python: >=3.7
License-File: LICENSE
Provides-Extra: full
Requires-Dist: Pillow; extra == "full"
Requires-Dist: numpy; extra == "full"
Provides-Extra: test
Requires-Dist: pytest; extra == "test"
Provides-Extra: lint
Requires-Dist: ruff; extra == "lint"
Requires-Dist: mypy; extra == "lint"
Requires-Dist: isort; extra == "lint"
Requires-Dist: types-Pillow; extra == "lint"
Dynamic: license-file
